carrottransform/__init__.py
carrottransform/_version.py
carrottransform/cli/__init__.py
carrottransform/cli/command.py
carrottransform/cli/subcommands/__init__.py
carrottransform/cli/subcommands/run.py
carrottransform/cli/subcommands/run_v2.py
carrottransform/config/OMOPCDM_postgresql_5.3_ddl.sql
carrottransform/config/OMOPCDM_postgresql_5.4_ddl.sql
carrottransform/config/config.json
carrottransform/examples/test/inputs/Covid19_test.csv
carrottransform/examples/test/inputs/Demographics.csv
carrottransform/examples/test/inputs/Symptoms.csv
carrottransform/examples/test/inputs/covid19_antibody.csv
carrottransform/examples/test/inputs/vaccine.csv
carrottransform/examples/test/output/condition_occurrence.tsv
carrottransform/examples/test/output/measurement.tsv
carrottransform/examples/test/output/observation.tsv
carrottransform/examples/test/output/person.tsv
carrottransform/examples/test/output/person_ids.tsv
carrottransform/examples/test/output/summary_mapstream.tsv
carrottransform/examples/test/rules/rules_14June2021.json
carrottransform/examples/test/rules/v1.json
carrottransform/examples/test/rules/v2-db-conn.json
carrottransform/examples/test/rules/v2.json
carrottransform/tools/__init__.py
carrottransform/tools/args.py
carrottransform/tools/concept_helpers.py
carrottransform/tools/core.py
carrottransform/tools/date_helpers.py
carrottransform/tools/db.py
carrottransform/tools/file_helpers.py
carrottransform/tools/logger.py
carrottransform/tools/mapping_types.py
carrottransform/tools/mappingrules.py
carrottransform/tools/metrics.py
carrottransform/tools/omopcdm.py
carrottransform/tools/orchestrator.py
carrottransform/tools/outputs.py
carrottransform/tools/person_helpers.py
carrottransform/tools/record_builder.py
carrottransform/tools/sources.py
carrottransform/tools/stream_helpers.py
carrottransform/tools/types.py
carrottransform/tools/validation.py
carrot_transform-0.6.1.dist-info/METADATA
carrot_transform-0.6.1.dist-info/WHEEL
carrot_transform-0.6.1.dist-info/entry_points.txt
carrot_transform-0.6.1.dist-info/licenses/LICENSE
carrot_transform-0.6.1.dist-info/RECORD
