Metadata-Version: 2.4
Name: carrot_transform
Version: 0.6.1
Author-email: anwarfg <913028+anwarfg@users.noreply.github.com>
License-Expression: MIT
License-File: LICENSE
Requires-Python: >=3.10
Requires-Dist: awscli>=1.42.74
Requires-Dist: boto3>=1.40.74
Requires-Dist: click<9,>=8.1.7
Requires-Dist: psycopg2-binary>=2.9.10
Requires-Dist: sqlalchemy>=2.0.42
Requires-Dist: trino>=0.335.0
